django_gerente/__init__.py
django_gerente/__main__.py
django_gerente-0.0.2.dist-info/licenses/LICENSE
django_gerente-0.0.2.dist-info/METADATA
django_gerente-0.0.2.dist-info/WHEEL
django_gerente-0.0.2.dist-info/top_level.txt
django_gerente-0.0.2.dist-info/RECORD
